pdfbyte/__init__.py
pdfbyte/utils.py
pdfbyte-0.1.1.dist-info/licenses/LICENSE
pdfbyte-0.1.1.dist-info/METADATA
pdfbyte-0.1.1.dist-info/WHEEL
pdfbyte-0.1.1.dist-info/top_level.txt
pdfbyte-0.1.1.dist-info/RECORD
