Metadata-Version: 2.4
Name: pdfbyte
Version: 0.1.1
Summary: A simple package for working with PDFs
Author: Ramesh Chandra
Author-email: rameshsofter@gmail.com
Classifier: Programming Language :: Python :: 3
Classifier: License :: OSI Approved :: MIT License
Classifier: Operating System :: OS Independent
Requires-Python: >=3.6
License-File: LICENSE
Dynamic: author
Dynamic: author-email
Dynamic: classifier
Dynamic: description
Dynamic: description-content-type
Dynamic: license-file
Dynamic: requires-python
Dynamic: summary
